miniwdl_backend_bare/__init__.py
miniwdl_backend_bare/bare.py
miniwdl_backend_bare-0.0.1.dist-info/METADATA
miniwdl_backend_bare-0.0.1.dist-info/WHEEL
miniwdl_backend_bare-0.0.1.dist-info/entry_points.txt
miniwdl_backend_bare-0.0.1.dist-info/licenses/LICENSE
miniwdl_backend_bare-0.0.1.dist-info/RECORD
