Metadata-Version: 2.1
Name: miniwdl-backend-bare
Version: 0.0.1
Summary: miniwdl bare backend
License-File: LICENSE
Requires-Python: >=3.6
Requires-Dist: miniwdl>=1.9.0
